cmsis_posmsk_codegen
