Metadata-Version: 2.1
Name: cmsis-posmsk-codegen
Version: 2
Summary: small utility to generate Pos and Msk definitions for registers, particularly for CMSIS projects
Home-page: https://github.com/metebalci/cmsis_posmsk_codegen
Author: Mete Balci
Author-email: metebalci@gmail.com
License: GPLv3
Keywords: cmsis register pos msk
Platform: UNKNOWN
Classifier: Development Status :: 3 - Alpha
Classifier: Environment :: Console
Classifier: Intended Audience :: Developers
Classifier: License :: OSI Approved :: GNU General Public License v3 (GPLv3)
Classifier: Topic :: Utilities
Classifier: Programming Language :: Python :: 3.6
